cvesearcher/__init__.py
cvesearcher/search.py
cvesearcher-0.1.0.dist-info/METADATA
cvesearcher-0.1.0.dist-info/WHEEL
cvesearcher-0.1.0.dist-info/entry_points.txt
cvesearcher-0.1.0.dist-info/top_level.txt
cvesearcher-0.1.0.dist-info/RECORD
