Metadata-Version: 2.1
Name: cvesearcher
Version: 0.1.0
Summary: A Python library for searching CVEs using NVD API
Author: gnuestae
Author-email: hi563@naever.com
Classifier: Programming Language :: Python :: 3
Classifier: License :: OSI Approved :: MIT License
Classifier: Operating System :: OS Independent
Requires-Python: >=3.6
Requires-Dist: requests
